LICENSE
MANIFEST.in
README.md
quicktest.py
settings_test.py
setup.py
django_vkontakte_groups_statistic.egg-info/PKG-INFO
django_vkontakte_groups_statistic.egg-info/SOURCES.txt
django_vkontakte_groups_statistic.egg-info/dependency_links.txt
django_vkontakte_groups_statistic.egg-info/not-zip-safe
django_vkontakte_groups_statistic.egg-info/requires.txt
django_vkontakte_groups_statistic.egg-info/top_level.txt
vkontakte_groups_statistic/__init__.py
vkontakte_groups_statistic/__init__.pyc
vkontakte_groups_statistic/admin.py
vkontakte_groups_statistic/admin.pyc
vkontakte_groups_statistic/factories.py
vkontakte_groups_statistic/factories.pyc
vkontakte_groups_statistic/forms.py
vkontakte_groups_statistic/forms.pyc
vkontakte_groups_statistic/models.py
vkontakte_groups_statistic/models.pyc
vkontakte_groups_statistic/tests.py
vkontakte_groups_statistic/tests.pyc
vkontakte_groups_statistic/views.py
vkontakte_groups_statistic/views.pyc
vkontakte_groups_statistic/migrations/0001_initial.py
vkontakte_groups_statistic/migrations/0001_initial.pyc
vkontakte_groups_statistic/migrations/0002_auto__add_field_groupstat_hidings.py
vkontakte_groups_statistic/migrations/0002_auto__add_field_groupstat_hidings.pyc
vkontakte_groups_statistic/migrations/0003_auto__add_field_groupstat_traffic_search_systems__add_field_groupstat_.py
vkontakte_groups_statistic/migrations/0003_auto__add_field_groupstat_traffic_search_systems__add_field_groupstat_.pyc
vkontakte_groups_statistic/migrations/0004_auto__add_field_groupstat_traffic_ads__add_field_groupstat_traffic_rec.py
vkontakte_groups_statistic/migrations/0004_auto__add_field_groupstat_traffic_ads__add_field_groupstat_traffic_rec.pyc
vkontakte_groups_statistic/migrations/0005_auto__del_field_groupstat_traffic_external_sites__del_field_groupstat_.py
vkontakte_groups_statistic/migrations/0005_auto__del_field_groupstat_traffic_external_sites__del_field_groupstat_.pyc
vkontakte_groups_statistic/migrations/0006_auto__add_field_groupstat_sources_audio.py
vkontakte_groups_statistic/migrations/0006_auto__add_field_groupstat_sources_audio.pyc
vkontakte_groups_statistic/migrations/0007_auto.py
vkontakte_groups_statistic/migrations/0007_auto.pyc
vkontakte_groups_statistic/migrations/0008_auto__add_field_groupstat_period.py
